dxclient/__init__.py
dxclient/client.py
dxclient/config.py
dxclient/store.py
deployx_server_sdk-1.0.9.dist-info/LICENSE
deployx_server_sdk-1.0.9.dist-info/METADATA
deployx_server_sdk-1.0.9.dist-info/WHEEL
deployx_server_sdk-1.0.9.dist-info/top_level.txt
deployx_server_sdk-1.0.9.dist-info/RECORD
